arabic2latin/__init__.py
arabic2latin/arabic2latin.py
arabic2latin/version.py
arabic2latin-1.1.4.dist-info/LICENSE
arabic2latin-1.1.4.dist-info/METADATA
arabic2latin-1.1.4.dist-info/WHEEL
arabic2latin-1.1.4.dist-info/top_level.txt
arabic2latin-1.1.4.dist-info/RECORD
