Metadata-Version: 2.1
Name: arabic2latin
Version: 1.1.4
Summary: Convert Arabic characters to their Latin (English) homophones.
Author: rexa222
Author-email: rexa222@outlook.com
License: MIT License
Project-URL: Homepage, https://github.com/rexa222/arabic2latin
Project-URL: Bug Tracker, https://github.com/rexa222/arabic2latin/issues
Keywords: arabic,homophone,arabic to english,arabic to latin
Classifier: Development Status :: 5 - Production/Stable
Classifier: Intended Audience :: Developers
Classifier: License :: OSI Approved :: MIT License
Classifier: Topic :: Software Development :: Libraries
Classifier: Programming Language :: Python :: 3
Classifier: Typing :: Typed
Requires-Python: >=3.6
License-File: LICENSE
